Metadata-Version: 2.1
Name: jiramenu
Version: 1.0.12
Summary: dmenu/rofi frontend for jira
Home-page: https://github.com/ljurk/jiramenu
Author: Lukas Jurk
Author-email: ljurk@pm.me
License: GPLv3
Keywords: jira dmenu rofi
Platform: UNKNOWN
Classifier: Programming Language :: Python :: 2
Classifier: Programming Language :: Python :: 3
